sectool/__init__.py
sectool/sectool.py
sectool-0.0.17.dist-info/LICENSE
sectool-0.0.17.dist-info/METADATA
sectool-0.0.17.dist-info/WHEEL
sectool-0.0.17.dist-info/top_level.txt
sectool-0.0.17.dist-info/RECORD
