Metadata-Version: 2.1
Name: sectool
Version: 0.0.17
Summary: A tool for keeping secrets during software builds and deployments
Home-page: https://github.com/ivaganov/sectool.git
Author: Ivan Vaganov
Author-email: ivaganov@gmail.com
License: UNKNOWN
Project-URL: Bug Tracker, https://github.com/ivaganov/sectool/issues
Platform: UNKNOWN
Classifier: Programming Language :: Python :: 3
Classifier: License :: OSI Approved :: MIT License
Classifier: Operating System :: OS Independent
Requires-Python: >=3.7
License-File: LICENSE
